zm_au/__init__.py
zm_au/base.py
zm_au/pip/__init__.py
zm_au/pip/base.py
zm_au/pip/github.py
zm_au-2.0.0.dist-info/LICENSE
zm_au-2.0.0.dist-info/METADATA
zm_au-2.0.0.dist-info/WHEEL
zm_au-2.0.0.dist-info/RECORD
