Metadata-Version: 2.1
Name: zm-au
Version: 2.0.0
Summary: Auto-updater for programs
Home-page: https://github.com/zmarffy/au
License: MIT
Author: Zeke Marffy
Author-email: zmarffy@yahoo.com
Requires-Python: >=3.8.1,<4.0.0
Classifier: License :: OSI Approved :: MIT License
Classifier: Programming Language :: Python :: 3
Classifier: Programming Language :: Python :: 3.9
Classifier: Programming Language :: Python :: 3.10
Classifier: Programming Language :: Python :: 3.11
Requires-Dist: install-directives (>=1.0.0,<2.0.0)
Requires-Dist: packaging (>=22.0,<23.0)
Requires-Dist: requests (>=2.28.2,<3.0.0)
Requires-Dist: zmtools (>=3.0.0,<4.0.0)
Project-URL: Repository, https://github.com/zmarffy/au
